CHANGES.txt
CONTRIBUTORS.txt
MANIFEST.in
README.rst
setup.py
docs/LICENSE.GPL
docs/LICENSE.txt
inigo/__init__.py
inigo.ploneanalyticswrapper.egg-info/PKG-INFO
inigo.ploneanalyticswrapper.egg-info/SOURCES.txt
inigo.ploneanalyticswrapper.egg-info/dependency_links.txt
inigo.ploneanalyticswrapper.egg-info/entry_points.txt
inigo.ploneanalyticswrapper.egg-info/namespace_packages.txt
inigo.ploneanalyticswrapper.egg-info/not-zip-safe
inigo.ploneanalyticswrapper.egg-info/requires.txt
inigo.ploneanalyticswrapper.egg-info/top_level.txt
inigo/ploneanalyticswrapper/__init__.py
inigo/ploneanalyticswrapper/configure.zcml
inigo/ploneanalyticswrapper/interfaces.py
inigo/ploneanalyticswrapper/viewlet.py
inigo/ploneanalyticswrapper/profiles/default/browserlayer.xml
inigo/ploneanalyticswrapper/profiles/default/metadata.xml