Metadata-Version: 1.1
Name: inigo.ploneanalyticswrapper
Version: 1.0
Summary: A wrapper for plone.analytics viewlet which adds a selectable DIV around it
Home-page: https://github.com/inigoconsulting/inigo.ploneanalyticswrapper
Author: Inigo Consulting
Author-email: team@inigo-tech.com
License: gpl
Keywords: plone analytics wrapper python
Platform: UNKNOWN
Classifier: Programming Language :: Python
